django_observe/__init__.py
django_observe/apps.py
django_observe/middleware.py
django_observe/models.py
django_observe/urls.py
django_observe/views.py
django_observe/migrations/0001_initial.py
django_observe/migrations/0002_alter_event_timestamp.py
django_observe/migrations/0003_alter_event_timestamp.py
django_observe/migrations/__init__.py
django_observe/static/django_observe/chart.min.js
django_observe/static/django_observe/chart.umd.min.js
django_observe/static/django_observe/chartjs-adapter-date-fns.bundle.min.js
django_observe/static/django_observe/tailwind.js
django_observe/templates/django_observe/glass.html
django_observe-0.2.0.dist-info/LICENSE
django_observe-0.2.0.dist-info/METADATA
django_observe-0.2.0.dist-info/WHEEL
django_observe-0.2.0.dist-info/top_level.txt
django_observe-0.2.0.dist-info/RECORD
